MANIFEST.in
NEWS.txt
README.rst
setup.py
rainbow_saddle.egg-info/PKG-INFO
rainbow_saddle.egg-info/SOURCES.txt
rainbow_saddle.egg-info/dependency_links.txt
rainbow_saddle.egg-info/entry_points.txt
rainbow_saddle.egg-info/not-zip-safe
rainbow_saddle.egg-info/pbr.json
rainbow_saddle.egg-info/requires.txt
rainbow_saddle.egg-info/top_level.txt
rainbowsaddle/__init__.py
tests/__init__.py
tests/test_functional.py
tests/wsgi_1.py
tests/wsgi_2.py