Metadata-Version: 1.1
Name: rainbow-saddle
Version: 0.4.0
Summary: A wrapper around gunicorn to handle graceful restarts correctly
Home-page: https://github.com/flupke/rainbow-saddle
Author: Luper Rouch
Author-email: luper.rouch@gmail.com
License: BSD
Keywords: gunicorn wrapper graceful restart
Platform: UNKNOWN
Classifier: License :: OSI Approved :: BSD License
Classifier: Topic :: Internet :: WWW/HTTP :: WSGI :: Server
